mipsplusplus/__init__.py
mipsplusplus/__main__.py
mipsplusplus/addresses.py
mipsplusplus/definitions.py
mipsplusplus/expressions.py
mipsplusplus/functions.py
mipsplusplus/general.py
mipsplusplus/main.py
mipsplusplus/operations.py
mipsplusplus/parser.py
mipsplusplus/utils.py
mipsplusplus-0.0.1b4.dist-info/METADATA
mipsplusplus-0.0.1b4.dist-info/RECORD
mipsplusplus-0.0.1b4.dist-info/WHEEL
mipsplusplus-0.0.1b4.dist-info/top_level.txt
