Metadata-Version: 2.1
Name: mipsplusplus
Version: 0.0.1b4
Summary: A low-level programming language based on the MIPS architecture.
Home-page: https://github.com/alexsocha/mipsplusplus
Author: Alex Socha
Author-email: alex@alexsocha.com
License: UNKNOWN
Platform: UNKNOWN
Classifier: Programming Language :: Python :: 3
Classifier: License :: OSI Approved :: MIT License
Classifier: Operating System :: OS Independent
